pinggutools/__init__.py
pinggutools/def.py
pinggutools/pinggutools.py
pinggutools-1.0.0.dist-info/LICENSE
pinggutools-1.0.0.dist-info/METADATA
pinggutools-1.0.0.dist-info/WHEEL
pinggutools-1.0.0.dist-info/entry_points.txt
pinggutools-1.0.0.dist-info/top_level.txt
pinggutools-1.0.0.dist-info/RECORD
