Metadata-Version: 2.1
Name: pinggutools
Version: 1.0.0
Summary: RTS
Home-page: https://mp.weixin.qq.com/s/-yNaCn9aU855cxMXD7W4eQ
Author: sysucai
Author-email: 411703730@qq.com
Platform: Any platform -- don't need Windows
Classifier: Programming Language :: Python :: 3
Classifier: License :: OSI Approved :: MIT License
Classifier: Operating System :: OS Independent
License-File: LICENSE
Requires-Dist: pandas >=1.3.4
Requires-Dist: numpy >=1.21.3
Requires-Dist: xlrd >=2.0.1
Requires-Dist: xlwt >=1.3.0
Requires-Dist: openpyxl >=3.0.9
Requires-Dist: xlsxwriter >=3.0.1
Requires-Dist: matplotlib >=3.4.3
Requires-Dist: requests >=2.28.1
